autossl/__init__.py
autossl/certificates.py
autossl/info.py
autossl/ca_api/__init__.py
autossl/ca_api/ca.py
autossl/ca_api/digicert.py
autossl/keygen/__init__.py
autossl/keygen/csr.py
autossl/keygen/pvtkey.py
sslauto/__init__.py
sslauto/certificates.py
sslauto/info.py
sslauto/ca_api/__init__.py
sslauto/ca_api/ca.py
sslauto/ca_api/digicert.py
sslauto/keygen/__init__.py
sslauto/keygen/csr.py
sslauto/keygen/pvtkey.py
sslauto-0.1.24.dist-info/LICENSE
sslauto-0.1.24.dist-info/METADATA
sslauto-0.1.24.dist-info/WHEEL
sslauto-0.1.24.dist-info/top_level.txt
sslauto-0.1.24.dist-info/RECORD
