Metadata-Version: 2.2
Name: sslauto
Version: 0.1.24
Summary: Automate your digital certificate workflows.
Author-email: Chris Torok <torok.chris@gmail.com>
License: MIT License
Project-URL: Homepage, https://github.com/thetisrock
Classifier: Programming Language :: Python :: 3
Classifier: Operating System :: OS Independent
Requires-Python: >=3.13
License-File: LICENSE
Requires-Dist: requests>=2.32.3
Requires-Dist: cryptography>=44.0.0
